immutability/__init__.py
immutability/this.py
immutability-0.1.dist-info/LICENSE
immutability-0.1.dist-info/METADATA
immutability-0.1.dist-info/WHEEL
immutability-0.1.dist-info/top_level.txt
immutability-0.1.dist-info/RECORD
