Metadata-Version: 2.1
Name: immutability
Version: 0.1
Summary: Functional programming tools in Python
Author: Brian Yue
License: UNKNOWN
Platform: UNKNOWN
Classifier: Programming Language :: Python :: 3
Classifier: License :: OSI Approved :: MIT License
Classifier: Operating System :: OS Independent
Requires-Python: >=3.6
License-File: LICENSE
